{
    "elevation": 26.0,
    "hourly": {
        "rain": [
            0.0,
            0.0,
            0.0,
            0.0,
            0.0,
            0.0,
            0.0,
            0.0,
            0.0,
            0.0,
            0.0,
            0.0,
            0.0,
            0.0,
            0.0,
            0.0,
            0.9,
            2.6,
            0.4,
            0.0,
            0.0,
            0.0,
            0.0,
            0.0
        ],
        "temperature_2m": [
            9.8,
            9.4,
            9.3,
            9.7,
            9.3,
            9.0,
            9.1,
            8.7,
            8.5,
            8.8,
            9.3,
            10.1,
            10.6,
            10.5,
            10.1,
            9.7,
            9.6,
            9.6,
            10.1,
            11.1,
            11.2,
            11.1,
            10.7,
            10.2
        ],
        "time": [
            "2023-12-10T00:00",
            "2023-12-10T01:00",
            "2023-12-10T02:00",
            "2023-12-10T03:00",
            "2023-12-10T04:00",
            "2023-12-10T05:00",
            "2023-12-10T06:00",
            "2023-12-10T07:00",
            "2023-12-10T08:00",
            "2023-12-10T09:00",
            "2023-12-10T10:00",
            "2023-12-10T11:00",
            "2023-12-10T12:00",
            "2023-12-10T13:00",
            "2023-12-10T14:00",
            "2023-12-10T15:00",
            "2023-12-10T16:00",
            "2023-12-10T17:00",
            "2023-12-10T18:00",
            "2023-12-10T19:00",
            "2023-12-10T20:00",
            "2023-12-10T21:00",
            "2023-12-10T22:00",
            "2023-12-10T23:00"
        ],
        "windspeed_10m": [
            23.7,
            23.4,
            24.6,
            24.5,
            23.9,
            22.3,
            20.8,
            21.1,
            19.5,
            16.6,
            16.7,
            17.6,
            23.6,
            22.3,
            20.3,
            17.8,
            16.5,
            21.1,
            24.0,
            24.0,
            21.8,
            19.2,
            16.3,
            17.7
        ]
    },
    "hourly_units": {
        "rain": "mm",
        "temperature_2m": "\u00b0C",
        "time": "iso8601",
        "windspeed_10m": "km/h"
    },
    "latitude": 50.86,
    "longitude": 4.36,
    "timezone": "GMT",
    "timezone_abbreviation": "GMT",
    "utc_offset_seconds": 0
}