{
    "elevation": 48.0,
    "hourly": {
        "rain": [
            2.2,
            0.3,
            0.0,
            0.0,
            0.0,
            1.0,
            0.7,
            1.1,
            2.0,
            1.2,
            0.8,
            0.9,
            0.6,
            0.2,
            0.0,
            0.0,
            0.0,
            0.0,
            0.1,
            0.2,
            0.2,
            0.1,
            0.1,
            0.1
        ],
        "temperature_2m": [
            5.1,
            5.1,
            5.2,
            5.2,
            5.6,
            5.8,
            5.8,
            5.9,
            5.9,
            5.8,
            5.6,
            5.6,
            5.7,
            5.9,
            6.3,
            6.1,
            5.6,
            5.4,
            5.0,
            4.3,
            4.1,
            4.2,
            4.3,
            4.3
        ],
        "time": [
            "2023-11-14T00:00",
            "2023-11-14T01:00",
            "2023-11-14T02:00",
            "2023-11-14T03:00",
            "2023-11-14T04:00",
            "2023-11-14T05:00",
            "2023-11-14T06:00",
            "2023-11-14T07:00",
            "2023-11-14T08:00",
            "2023-11-14T09:00",
            "2023-11-14T10:00",
            "2023-11-14T11:00",
            "2023-11-14T12:00",
            "2023-11-14T13:00",
            "2023-11-14T14:00",
            "2023-11-14T15:00",
            "2023-11-14T16:00",
            "2023-11-14T17:00",
            "2023-11-14T18:00",
            "2023-11-14T19:00",
            "2023-11-14T20:00",
            "2023-11-14T21:00",
            "2023-11-14T22:00",
            "2023-11-14T23:00"
        ],
        "windspeed_10m": [
            25.6,
            25.6,
            23.4,
            25.9,
            24.1,
            25.2,
            26.3,
            25.9,
            29.9,
            32.8,
            33.5,
            30.2,
            30.2,
            29.2,
            29.2,
            29.5,
            25.6,
            23.8,
            19.4,
            19.8,
            19.4,
            17.6,
            15.8,
            14.8
        ]
    },
    "hourly_units": {
        "rain": "mm",
        "temperature_2m": "\u00b0C",
        "time": "iso8601",
        "windspeed_10m": "km/h"
    },
    "latitude": 55.707832,
    "longitude": 13.18663,
    "timezone": "GMT",
    "timezone_abbreviation": "GMT",
    "utc_offset_seconds": 0
}