{
    "elevation": 55.0,
    "hourly": {
        "rain": [
            0.0,
            0.0,
            0.0,
            0.0,
            0.0,
            0.0,
            0.0,
            0.0,
            0.0,
            0.0,
            0.0,
            0.0,
            0.0,
            0.0,
            0.0,
            0.0,
            0.0,
            0.0,
            0.0,
            0.0,
            0.0,
            0.0,
            0.0,
            0.0
        ],
        "temperature_2m": [
            8.0,
            8.1,
            8.1,
            8.1,
            7.9,
            7.6,
            7.7,
            8.4,
            9.7,
            12.1,
            13.3,
            13.6,
            13.6,
            13.2,
            13.4,
            13.5,
            13.5,
            13.1,
            13.2,
            13.2,
            13.5,
            13.8,
            13.7,
            13.7
        ],
        "time": [
            "2023-12-21T00:00",
            "2023-12-21T01:00",
            "2023-12-21T02:00",
            "2023-12-21T03:00",
            "2023-12-21T04:00",
            "2023-12-21T05:00",
            "2023-12-21T06:00",
            "2023-12-21T07:00",
            "2023-12-21T08:00",
            "2023-12-21T09:00",
            "2023-12-21T10:00",
            "2023-12-21T11:00",
            "2023-12-21T12:00",
            "2023-12-21T13:00",
            "2023-12-21T14:00",
            "2023-12-21T15:00",
            "2023-12-21T16:00",
            "2023-12-21T17:00",
            "2023-12-21T18:00",
            "2023-12-21T19:00",
            "2023-12-21T20:00",
            "2023-12-21T21:00",
            "2023-12-21T22:00",
            "2023-12-21T23:00"
        ],
        "windspeed_10m": [
            17.2,
            18.0,
            13.8,
            12.4,
            9.5,
            7.3,
            7.2,
            9.2,
            11.6,
            19.2,
            22.7,
            25.5,
            23.1,
            20.6,
            23.0,
            19.7,
            23.0,
            23.5,
            19.8,
            16.9,
            16.8,
            23.0,
            25.6,
            25.3
        ]
    },
    "hourly_units": {
        "rain": "mm",
        "temperature_2m": "\u00b0C",
        "time": "iso8601",
        "windspeed_10m": "km/h"
    },
    "latitude": 43.6,
    "longitude": 3.8799996,
    "timezone": "GMT",
    "timezone_abbreviation": "GMT",
    "utc_offset_seconds": 0
}