{
    "elevation": 521.0,
    "hourly": {
        "rain": [
            0.0,
            0.0,
            0.0,
            0.0,
            0.0,
            0.0,
            0.0,
            0.0,
            0.0,
            0.0,
            0.0,
            0.0,
            0.0,
            0.0,
            0.0,
            0.0,
            0.0,
            0.0,
            0.0,
            0.0,
            0.0,
            0.0,
            0.0,
            0.0
        ],
        "temperature_2m": [
            10.7,
            9.5,
            9.4,
            9.0,
            9.1,
            9.3,
            9.1,
            9.3,
            11.2,
            12.8,
            14.3,
            15.1,
            16.3,
            16.6,
            16.7,
            16.2,
            15.0,
            14.0,
            13.5,
            12.9,
            12.1,
            11.5,
            10.9,
            10.5
        ],
        "time": [
            "2023-11-19T00:00",
            "2023-11-19T01:00",
            "2023-11-19T02:00",
            "2023-11-19T03:00",
            "2023-11-19T04:00",
            "2023-11-19T05:00",
            "2023-11-19T06:00",
            "2023-11-19T07:00",
            "2023-11-19T08:00",
            "2023-11-19T09:00",
            "2023-11-19T10:00",
            "2023-11-19T11:00",
            "2023-11-19T12:00",
            "2023-11-19T13:00",
            "2023-11-19T14:00",
            "2023-11-19T15:00",
            "2023-11-19T16:00",
            "2023-11-19T17:00",
            "2023-11-19T18:00",
            "2023-11-19T19:00",
            "2023-11-19T20:00",
            "2023-11-19T21:00",
            "2023-11-19T22:00",
            "2023-11-19T23:00"
        ],
        "windspeed_10m": [
            6.4,
            5.4,
            5.9,
            7.6,
            7.6,
            7.9,
            7.7,
            8.9,
            10.7,
            14.3,
            14.2,
            13.6,
            13.5,
            9.2,
            10.1,
            8.8,
            7.0,
            8.2,
            8.4,
            7.4,
            7.0,
            6.0,
            6.5,
            6.8
        ]
    },
    "hourly_units": {
        "rain": "mm",
        "temperature_2m": "\u00b0C",
        "time": "iso8601",
        "windspeed_10m": "km/h"
    },
    "latitude": 45.44,
    "longitude": 4.3799996,
    "timezone": "GMT",
    "timezone_abbreviation": "GMT",
    "utc_offset_seconds": 0
}