{
    "elevation": 18.0,
    "hourly": {
        "rain": [
            0.0,
            0.0,
            0.0,
            0.0,
            0.0,
            0.0,
            0.0,
            0.0,
            0.0,
            0.0,
            0.0,
            0.0,
            0.0,
            0.0,
            0.0,
            0.0,
            0.0,
            0.0,
            0.0,
            0.0,
            0.0,
            0.0,
            0.0,
            0.0
        ],
        "temperature_2m": [
            22.4,
            21.7,
            21.3,
            20.8,
            20.3,
            19.9,
            19.8,
            21.3,
            24.4,
            27.8,
            30.7,
            33.3,
            35.7,
            37.3,
            38.4,
            38.9,
            39.0,
            38.8,
            36.6,
            33.7,
            30.5,
            29.1,
            28.2,
            27.5
        ],
        "time": [
            "2023-07-29T00:00",
            "2023-07-29T01:00",
            "2023-07-29T02:00",
            "2023-07-29T03:00",
            "2023-07-29T04:00",
            "2023-07-29T05:00",
            "2023-07-29T06:00",
            "2023-07-29T07:00",
            "2023-07-29T08:00",
            "2023-07-29T09:00",
            "2023-07-29T10:00",
            "2023-07-29T11:00",
            "2023-07-29T12:00",
            "2023-07-29T13:00",
            "2023-07-29T14:00",
            "2023-07-29T15:00",
            "2023-07-29T16:00",
            "2023-07-29T17:00",
            "2023-07-29T18:00",
            "2023-07-29T19:00",
            "2023-07-29T20:00",
            "2023-07-29T21:00",
            "2023-07-29T22:00",
            "2023-07-29T23:00"
        ],
        "windspeed_10m": [
            6.2,
            1.9,
            2.0,
            2.2,
            3.2,
            3.6,
            3.0,
            2.5,
            2.9,
            2.4,
            1.5,
            2.2,
            2.6,
            5.0,
            6.6,
            9.2,
            10.3,
            11.6,
            18.9,
            16.5,
            14.6,
            9.4,
            5.9,
            3.6
        ]
    },
    "hourly_units": {
        "rain": "mm",
        "temperature_2m": "\u00b0C",
        "time": "iso8601",
        "windspeed_10m": "km/h"
    },
    "latitude": 37.375,
    "longitude": -6.0,
    "timezone": "GMT",
    "timezone_abbreviation": "GMT",
    "utc_offset_seconds": 0
}